pbreflect/__init__.py
pbreflect/log.py
pbreflect/main.py
pbreflect/pbgen/__init__.py
pbreflect/pbgen/errors.py
pbreflect/pbgen/generators/__init__.py
pbreflect/pbgen/generators/base.py
pbreflect/pbgen/generators/factory.py
pbreflect/pbgen/generators/protocols.py
pbreflect/pbgen/generators/strategies/__init__.py
pbreflect/pbgen/generators/strategies/betterproto.py
pbreflect/pbgen/generators/strategies/default.py
pbreflect/pbgen/generators/strategies/dynamic.py
pbreflect/pbgen/generators/strategies/mypy.py
pbreflect/pbgen/generators/strategies/pbreflect.py
pbreflect/pbgen/patchers/__init__.py
pbreflect/pbgen/patchers/directory_structure_patcher.py
pbreflect/pbgen/patchers/import_patcher.py
pbreflect/pbgen/patchers/init_file_patcher.py
pbreflect/pbgen/patchers/mypy_patcher.py
pbreflect/pbgen/patchers/patcher_protocol.py
pbreflect/pbgen/patchers/pb_reflect_patcher.py
pbreflect/pbgen/patchers/proto_import_patcher.py
pbreflect/pbgen/plugins/__init__.py
pbreflect/pbgen/plugins/pbreflect/__init__.py
pbreflect/pbgen/plugins/pbreflect/templates/__init__.py
pbreflect/pbgen/plugins/pbreflect/templates/client.jinja2
pbreflect/pbgen/plugins/pbreflect_plugin.py
pbreflect/pbgen/runner.py
pbreflect/pbgen/utils/__init__.py
pbreflect/pbgen/utils/command.py
pbreflect/pbgen/utils/file_finder.py
pbreflect/pbgen/utils/format.py
pbreflect/protorecover/__init__.py
pbreflect/protorecover/proto_builder.py
pbreflect/protorecover/recover_service.py
pbreflect/protorecover/reflection_client.py
pbreflect/protorecover/templates/enum.proto.j2
pbreflect/protorecover/templates/file.proto.j2
pbreflect/protorecover/templates/message.proto.j2
pbreflect/protorecover/templates/service.proto.j2
pbreflect/utils.py
pbreflect-1.1.0.dist-info/LICENSE
pbreflect-1.1.0.dist-info/METADATA
pbreflect-1.1.0.dist-info/WHEEL
pbreflect-1.1.0.dist-info/entry_points.txt
pbreflect-1.1.0.dist-info/RECORD
