Metadata-Version: 2.1
Name: pbreflect
Version: 1.1.0
Summary: A tool for recovering Protocol Buffer definitions from gRPC services using reflection API and generating client code
Home-page: https://github.com/ValeriyMenshikov/pbreflect
License: MIT
Keywords: grpc,protobuf,reflection,proto,protocol-buffers,code-generation
Author: Menshikov Valeriy Sergeevich
Author-email: valery.menshikov.1989@gmail.com
Requires-Python: >=3.11,<4.0
Classifier: Development Status :: 4 - Beta
Classifier: Intended Audience :: Developers
Classifier: License :: OSI Approved :: MIT License
Classifier: Programming Language :: Python :: 3
Classifier: Programming Language :: Python :: 3.11
Classifier: Programming Language :: Python :: 3.12
Classifier: Programming Language :: Python :: 3.13
Classifier: Topic :: Software Development :: Code Generators
Classifier: Topic :: Software Development :: Libraries :: Python Modules
Provides-Extra: betterproto
Requires-Dist: betterproto (==v2.0.0-beta7) ; extra == "betterproto"
Requires-Dist: click (>=8.1.8)
Requires-Dist: grpc-stubs (>=1.53.0.6)
Requires-Dist: grpcio (>=1.71.0)
Requires-Dist: grpcio-reflection (>=1.71.0)
Requires-Dist: grpcio-tools (>=1.71.0)
Requires-Dist: jinja2 (>=3.1.6)
Requires-Dist: loguru (>=0.7.3)
Requires-Dist: mypy-protobuf (>=3.6.0)
Requires-Dist: protobuf (>=5.0.0)
Requires-Dist: pydantic (>=2.11.3)
Requires-Dist: pydantic-settings (>=2.9.1)
Requires-Dist: ruff (>=0.11.7)
Requires-Dist: types-protobuf (>=4.24.0.20240311)
Project-URL: Repository, https://github.com/ValeriyMenshikov/pbreflect
